blackgate/__init__.py
blackgate/cli.py
blackgate/component.py
blackgate/config.py
blackgate/daemon.py
blackgate/errors.py
blackgate/http_client.py
blackgate/http_proxy.py
blackgate/server.py
blackgate-0.3.0.dist-info/LICENSE
blackgate-0.3.0.dist-info/METADATA
blackgate-0.3.0.dist-info/WHEEL
blackgate-0.3.0.dist-info/entry_points.txt
blackgate-0.3.0.dist-info/top_level.txt
blackgate-0.3.0.dist-info/RECORD
