Metadata-Version: 2.1
Name: blackgate
Version: 0.3.0
Summary: Blackgate is an API gateway application.
Home-page: https://github.com/soasme/blackgate
Author: Ju Lin
Author-email: soasme@gmail.com
License: MIT
Keywords: microservices,api,gateway,server,production,
Platform: any
Classifier: Development Status :: 2 - Pre-Alpha
Classifier: Intended Audience :: Developers
Classifier: License :: OSI Approved :: MIT License
Classifier: Operating System :: OS Independent
Classifier: Programming Language :: Python
Classifier: Programming Language :: Python :: 3
Classifier: Programming Language :: Python :: 3.6
Requires-Dist: tornado (<6.0)
Requires-Dist: PyYAML (>=5.1.2)
Requires-Dist: click (>=5.0)
Requires-Dist: raven (>=6.10)
